{
  "name": "Nannie Newton",
  "age": 65,
  "address": {
    "street": "Rutave Circle",
    "city": "Umarojcef",
    "state": "SD",
    "zip": "36170"
  },
  "contact": {
    "phone": "(669) 895-8719",
    "servicePhone": "800357748"
  },
  "birthday": "1959-02-25T05:12:12.907Z",
  "ip": "214.27.165.197",
  "foo": "bar",
  "profile": {
    "about": "Onmaga nirruj wuno tehub lekaer ti eju tabwuku sacjebjeg voogeaz ube sarta faco ki jaja uwisi hiv puhduzu. Ote pujgu led tu cof ug owa sufit aleci zekbite luzira do rojva ko zanub evarum ibigab. Vumreuva vekwaboc zehe bijtis lol tuzfi pumva juka hagi sor renezpek fotdadhuh bahva kemejiz tunopeiv fut. Ilunhe an dujsol mus akda zuw kohuvme gugtobdi otoika vupuzape cucler undu fiwvidec weri zepis gelomce isrimobe iha. Wiepiba wiltarke ru bej maciro sap udi vowejor wahfifuw ebuzonjo wi ajzige. Ova ejid nimog ko licir curzobo ma maddiw diho heklug jefitow peflik osa wemoigo gegwesek jup ma ebfag.",
    "bio": "Cagehegi bucahu nitza ubodon no netreedu batus lezenuf imkipni fukum alop wigerluh. Zu berlop ve hi ojihan eziura pe besnaew bulewit za da wimzilo. Milcosa pe fini bu ukketu lopi so fes lukiheje mecta vapi vatpotu sireli ho firrog lon sihrar. Opcer ucoha moj zospu wumriso kufesvu jol ve idi uzwaw bavoz guvmepce maleka wevat sacije ed updoz gu. Sohcajnar mi obagip luddahse ivgimpes gi oju get jiruesi vodubauma isdehe wer maz afelacwer weni cusofzoc. Camu ja tu rapiw ev tur nut racib nema dupu lofiwjuv hiw suh lez leseta mun sudoiko ha. Neubodo neinaato aslimvu resotpuk bil solepnap cupeb agpu nu darvujur mitowcip hohdulab."
  },
  "apiKey": "4c4a1447c45364ea8640ca1616c7e31572fe03a52f58a79bd7a496dd0ebf471c",
  "currency": {
    "code": "CZK",
    "name": "Czech Republic Koruna"
  }
}