{
  "name": "Delia Ray",
  "age": 56,
  "address": {
    "street": "Suzev Place",
    "city": "Woftehci",
    "state": "WA",
    "zip": "83200"
  },
  "contact": {
    "phone": "(909) 773-3753",
    "servicePhone": "800246634"
  },
  "birthday": "1981-07-01T16:04:18.457Z",
  "ip": "49.175.237.110",
  "foo": "bar",
  "profile": {
    "about": "Pejbamas suhab cojel uburo jakkifi kulo mu ac zilfi witzo sor sijim femvu taspof ikgubdo gupce polumdah. Bu pi pu ram fezow nowazuw dar ha cugjirra jojik ta zusdof komci tadorodo kus man. Begnojcof bizosotom wi bo pohorjic de egukevlo gearubij mibe si jaculrir gonu foerruc opacmeg.",
    "bio": "Vaszuke ciwlougu co ekwako tar of na lefata zowe ajpozosi kimsegit rulolum va uf ti cug nazod. Owpe eltudwe visolu biv gaki tavahno duihora karug hatusike mucmi ani ekbusoj et leterdig fuvlowan unceras rasma. Zuzo gelahrah rib elti aswu uwituce deh vuaruru dupodsi wuc pojtop befjiete uloov igaebliz la on tam didpame. Ikisolhaw igwa judago cu arro lugbahtel susig ce vic ji otumab hijfe ucadi miordeb. Ov ma setof noviga sercais bik siideumo biib comutpi afce pikosaf pami koh sog it."
  },
  "apiKey": "c02ce91a5f74fd5277886c35bd364bf9b0bf3b1581cf50c750def1f4af898daf",
  "currency": {
    "code": "BOB",
    "name": "Bolivia Boliviano"
  }
}