{
  "name": "Eula Harrington",
  "age": 39,
  "address": {
    "street": "Nenri Heights",
    "city": "Tukhene",
    "state": "NJ",
    "zip": "98893"
  },
  "contact": {
    "phone": "(237) 266-5468",
    "servicePhone": "800592254"
  },
  "birthday": "1990-07-24T02:30:37.005Z",
  "ip": "205.25.104.170",
  "foo": "bar",
  "profile": {
    "about": "Eh imi wuwjusi ipmafku pufvej it loom fov jo pisfaf eco hu co rahor jifvalus azede zef. Vaote marreap zopuf li fuweb waw icsoofo iji tit ugzijgu wofeto pajaf denmif letukkot cezakun ocubul rellous zekluvka. Daulej ehho en de uricoso guezi ma suuj bekupe geh sej wedeco gagutwiw rejunrar akjon berak muzuk. Wugvoruz wag rur dobamhi bawogeg op kupselar uti kipas neh ojegifit fugama paljiw ok. Odo rupivu nuavoca jo ohanes dozrud vezsemhug jad zuna hum ak ga fi sajkor ujosogod wavuno. Meridze giovo zuagpil sohra bezgoca levapsod zibuz ve sajmiav pefi luoropol ifimosob go dar. Roravoki gihicpat zadabmo nowzaepi puvwusvej niejo moztej eka ozebinzop sofusru gi hof duhzel jafaga as ozorisij pucfede.",
    "bio": "Linjatpe ki tastego to vaderral itiica nucit uvajibfar setnum me astecsep facesobu miho dodgipuw. Ifu ewsevuc ehhumles dete lelje lude bid wezziw janu zesedni gouzazof aknanzoj ad ca ini hinakme ihivih kuremaba. Si oluf tuwzoc repe ji vezorkuz kojid efe zegaj wo zu no irzici mem. Voli cicjok om vot bog bi calmad jujafi uhopana laf vuczo piitiru co. Pepbig toira abcisaz juri ziremo tan sor ateje tehetu icdoto kuekebu ko kigke elfunse gor. To ruleli jijtik ofzo ugpib kilefe tiwho waujcik mumuwva ruf ac loagpu wokik dosva nomtoj ul lajpek."
  },
  "apiKey": "0281aff2512805d6db6f6107f52b0ff36ab8bc1d4abdcd3e2c4240ee965b737e",
  "currency": {
    "code": "TWD",
    "name": "Taiwan New Dollar"
  }
}